hand_recog/__init__.py
hand_recog/module.py
hand_recog-0.1.1.dist-info/METADATA
hand_recog-0.1.1.dist-info/WHEEL
hand_recog-0.1.1.dist-info/top_level.txt
hand_recog-0.1.1.dist-info/RECORD
