Metadata-Version: 2.4
Name: hand_recog
Version: 0.1.1
Summary: A package for hand recognition using MediaPipe and OpenCV
Requires-Dist: mediapipe>=0.8.9
Requires-Dist: opencv-python>=4.5.0
Dynamic: description
Dynamic: description-content-type
Dynamic: requires-dist
Dynamic: summary
